metorial_generated-1.0.6.dist-info/licenses/LICENSE
mt_2025_01_01_dashboard/__init__.py
mt_2025_01_01_dashboard/endpoints/__init__.py
mt_2025_01_01_dashboard/endpoints/api_keys.py
mt_2025_01_01_dashboard/endpoints/custom_servers.py
mt_2025_01_01_dashboard/endpoints/custom_servers_code.py
mt_2025_01_01_dashboard/endpoints/custom_servers_deployments.py
mt_2025_01_01_dashboard/endpoints/custom_servers_events.py
mt_2025_01_01_dashboard/endpoints/custom_servers_listing.py
mt_2025_01_01_dashboard/endpoints/custom_servers_managed_server_templates.py
mt_2025_01_01_dashboard/endpoints/custom_servers_remote_servers.py
mt_2025_01_01_dashboard/endpoints/custom_servers_versions.py
mt_2025_01_01_dashboard/endpoints/dashboard.py
mt_2025_01_01_dashboard/endpoints/dashboard_instance_custom_servers.py
mt_2025_01_01_dashboard/endpoints/dashboard_instance_custom_servers_code.py
mt_2025_01_01_dashboard/endpoints/dashboard_instance_custom_servers_deployments.py
mt_2025_01_01_dashboard/endpoints/dashboard_instance_custom_servers_events.py
mt_2025_01_01_dashboard/endpoints/dashboard_instance_custom_servers_listing.py
mt_2025_01_01_dashboard/endpoints/dashboard_instance_custom_servers_remote_servers.py
mt_2025_01_01_dashboard/endpoints/dashboard_instance_custom_servers_versions.py
mt_2025_01_01_dashboard/endpoints/dashboard_instance_files.py
mt_2025_01_01_dashboard/endpoints/dashboard_instance_links.py
mt_2025_01_01_dashboard/endpoints/dashboard_instance_provider_oauth_connections.py
mt_2025_01_01_dashboard/endpoints/dashboard_instance_provider_oauth_connections_authentications.py
mt_2025_01_01_dashboard/endpoints/dashboard_instance_provider_oauth_connections_events.py
mt_2025_01_01_dashboard/endpoints/dashboard_instance_provider_oauth_connections_profiles.py
mt_2025_01_01_dashboard/endpoints/dashboard_instance_provider_oauth_sessions.py
mt_2025_01_01_dashboard/endpoints/dashboard_instance_secrets.py
mt_2025_01_01_dashboard/endpoints/dashboard_instance_server_run_error_groups.py
metorial_generated-1.0.6.dist-info/METADATA
metorial_generated-1.0.6.dist-info/WHEEL
metorial_generated-1.0.6.dist-info/top_level.txt
metorial_generated-1.0.6.dist-info/RECORD
