Metadata-Version: 2.4
Name: metorial-generated
Version: 1.0.6
Summary: Generated SDK endpoints and resources for Metorial
Author-email: Metorial Team <support@metorial.com>
License: MIT
Project-URL: Homepage, https://metorial.com
Project-URL: Documentation, https://metorial.com/docs
Project-URL: Repository, https://github.com/metorial/metorial-python
Keywords: metorial,generated,sdk,endpoints
Classifier: Development Status :: 4 - Beta
Classifier: Intended Audience :: Developers
Classifier: Programming Language :: Python :: 3
Classifier: Programming Language :: Python :: 3.9
Classifier: Programming Language :: Python :: 3.10
Classifier: Programming Language :: Python :: 3.11
Classifier: Programming Language :: Python :: 3.12
Classifier: Topic :: Software Development :: Libraries :: Python Modules
Requires-Python: >=3.9
License-File: LICENSE
Requires-Dist: aiohttp>=3.8.0
Requires-Dist: typing-extensions>=4.0.0
Requires-Dist: metorial-core>=1.0.4
Requires-Dist: metorial-util-endpoint>=1.0.2
Dynamic: license-file
